[
  {
    "name": "Palm Bowl Kitchen",
    "cuisine": "Liberian",
    "neighborhood": "Sinkor",
    "price": "$$",
    "rating": 4.8,
    "bestTime": "Lunch",
    "specialty": "Palm butter rice bowl",
    "service": "Dine-in and takeaway",
    "description": "A steady lunch stop for palm butter, greens, and rice bowls prepared for quick midday service.",
    "image": "images/plate.svg"
  },
  {
    "name": "Atlantic Grill House",
    "cuisine": "Seafood",
    "neighborhood": "Mamba Point",
    "price": "$$$",
    "rating": 4.7,
    "bestTime": "Dinner",
    "specialty": "Grilled snapper",
    "service": "Reservations recommended",
    "description": "Known for grilled fish, bright sides, and a calm dinner setting near the ocean side of the city.",
    "image": "images/fish.svg"
  },
  {
    "name": "Broad Street Coffee Bar",
    "cuisine": "Cafe",
    "neighborhood": "Central Monrovia",
    "price": "$",
    "rating": 4.4,
    "bestTime": "Morning",
    "specialty": "Ginger coffee and pastries",
    "service": "Counter service",
    "description": "A compact coffee stop for breakfast meetings, pastries, and quick work sessions downtown.",
    "image": "images/cup.svg"
  },
  {
    "name": "Cassava Leaf Corner",
    "cuisine": "Liberian",
    "neighborhood": "Paynesville",
    "price": "$$",
    "rating": 4.6,
    "bestTime": "Lunch",
    "specialty": "Cassava leaf with rice",
    "service": "Family seating",
    "description": "A casual spot with generous plates of cassava leaf, fried plantain, and pepper sauce.",
    "image": "images/plate.svg"
  },
  {
    "name": "Congo Town Shawarma",
    "cuisine": "Middle Eastern",
    "neighborhood": "Congo Town",
    "price": "$",
    "rating": 4.3,
    "bestTime": "Evening",
    "specialty": "Chicken shawarma",
    "service": "Takeaway window",
    "description": "Fast evening wraps, grilled chicken, and fresh sauces for people moving through Congo Town.",
    "image": "images/wrap.svg"
  },
  {
    "name": "Pepper Coast Table",
    "cuisine": "Fusion",
    "neighborhood": "Sinkor",
    "price": "$$$",
    "rating": 4.5,
    "bestTime": "Dinner",
    "specialty": "Pepper chicken with coconut rice",
    "service": "Dine-in",
    "description": "A small dining room pairing familiar Liberian flavors with modern plating and seasonal sides.",
    "image": "images/plate.svg"
  },
  {
    "name": "Plantain Yard",
    "cuisine": "Vegetarian",
    "neighborhood": "Central Monrovia",
    "price": "$$",
    "rating": 4.2,
    "bestTime": "Afternoon",
    "specialty": "Roasted plantain platter",
    "service": "Outdoor seating",
    "description": "Plantain plates, bean stews, salads, and fresh juices served in a relaxed courtyard.",
    "image": "images/plantain.svg"
  },
  {
    "name": "Mesurado Brunch Room",
    "cuisine": "Cafe",
    "neighborhood": "Mamba Point",
    "price": "$$",
    "rating": 4.6,
    "bestTime": "Brunch",
    "specialty": "Eggs with spicy greens",
    "service": "Weekend brunch",
    "description": "A comfortable brunch stop with coffee, eggs, fruit bowls, and quiet indoor seating.",
    "image": "images/cup.svg"
  },
  {
    "name": "Jollof Junction",
    "cuisine": "West African",
    "neighborhood": "Paynesville",
    "price": "$",
    "rating": 4.4,
    "bestTime": "Lunch",
    "specialty": "Party jollof rice",
    "service": "Takeaway and delivery",
    "description": "Quick jollof plates with chicken, fish, or vegetables for dependable weekday meals.",
    "image": "images/rice.svg"
  },
  {
    "name": "Harbor Fruit Stand",
    "cuisine": "Juice",
    "neighborhood": "Central Monrovia",
    "price": "$",
    "rating": 4.1,
    "bestTime": "Morning",
    "specialty": "Pineapple ginger juice",
    "service": "Walk-up service",
    "description": "Fresh fruit cups and juices for a light breakfast or a cool stop during errands.",
    "image": "images/juice.svg"
  },
  {
    "name": "Sinkor Noodle Shop",
    "cuisine": "Asian",
    "neighborhood": "Sinkor",
    "price": "$$",
    "rating": 4.3,
    "bestTime": "Dinner",
    "specialty": "Vegetable stir-fry noodles",
    "service": "Dine-in and takeaway",
    "description": "Warm noodle bowls, stir-fried vegetables, and quick service for weeknight dinners.",
    "image": "images/noodles.svg"
  },
  {
    "name": "Beach Road Fish Fry",
    "cuisine": "Seafood",
    "neighborhood": "Mamba Point",
    "price": "$$",
    "rating": 4.5,
    "bestTime": "Sunset",
    "specialty": "Pepper fried fish",
    "service": "Casual outdoor tables",
    "description": "Fried fish, spicy pepper, and simple sides served in a casual sunset-friendly setting.",
    "image": "images/fish.svg"
  },
  {
    "name": "Red Light Rice House",
    "cuisine": "Liberian",
    "neighborhood": "Paynesville",
    "price": "$",
    "rating": 4.2,
    "bestTime": "Lunch",
    "specialty": "Check rice and gravy",
    "service": "Counter service",
    "description": "Affordable rice plates with rotating gravies for a filling local lunch.",
    "image": "images/rice.svg"
  },
  {
    "name": "Embassy Garden Cafe",
    "cuisine": "Cafe",
    "neighborhood": "Mamba Point",
    "price": "$$$",
    "rating": 4.6,
    "bestTime": "Afternoon",
    "specialty": "Iced coffee and sandwiches",
    "service": "Quiet seating",
    "description": "A polished cafe setting for sandwiches, coffee, and afternoon conversations.",
    "image": "images/cup.svg"
  },
  {
    "name": "Caldwell Pepper Soup",
    "cuisine": "West African",
    "neighborhood": "Congo Town",
    "price": "$$",
    "rating": 4.4,
    "bestTime": "Evening",
    "specialty": "Goat pepper soup",
    "service": "Group tables",
    "description": "A warm evening place for pepper soup, rice, and shared plates with friends.",
    "image": "images/soup.svg"
  }
]
